_transformerbeeclient_version.py
transformerbeeclient/__init__.py
transformerbeeclient/client.py
transformerbeeclient/protocols.py
transformerbeeclient/py.typed
transformerbeeclient/models/__init__.py
transformerbeeclient/models/boneycomb.py
transformerbeeclient/models/marktnachricht.py
transformerbeeclient/models/transformerapi.py
transformerbeeclient-0.2.3.dist-info/METADATA
transformerbeeclient-0.2.3.dist-info/WHEEL
transformerbeeclient-0.2.3.dist-info/licenses/LICENSE
transformerbeeclient-0.2.3.dist-info/RECORD
