Metadata-Version: 2.4
Name: transformerbeeclient
Version: 0.2.3
Summary: async HTTP client to communicate with transformer.bee/edifact-bo4e-converter
Project-URL: Changelog, https://github.com/Hochfrequenz/TransformerBeeClient.py/releases
Project-URL: Homepage, https://github.com/Hochfrequenz/TransformerBeeClient.py
Author-email: Hochfrequenz Unternehmensberatung GmbH <info+github@hochfrequenz.de>
License: MIT
License-File: LICENSE
Keywords: bo4e,edifact,transformer.bee
Classifier: Development Status :: 4 - Beta
Classifier: Environment :: Console
Classifier: Intended Audience :: Developers
Classifier: License :: OSI Approved :: MIT License
Classifier: Operating System :: OS Independent
Classifier: Programming Language :: Python
Classifier: Programming Language :: Python :: 3 :: Only
Classifier: Programming Language :: Python :: 3.11
Classifier: Programming Language :: Python :: 3.12
Classifier: Programming Language :: Python :: 3.13
Requires-Python: >=3.11
Requires-Dist: aioauth-client
Requires-Dist: aiohttp[speedups]>=3.9.3
Requires-Dist: efoli>=1.4.0
Requires-Dist: pydantic>=2.0.0
Requires-Dist: pyjwt
Provides-Extra: coverage
Requires-Dist: coverage==7.8.0; extra == 'coverage'
Provides-Extra: formatting
Requires-Dist: black==25.1.0; extra == 'formatting'
Requires-Dist: isort==6.0.1; extra == 'formatting'
Provides-Extra: linting
Requires-Dist: pylint==3.3.6; extra == 'linting'
Provides-Extra: packaging
Requires-Dist: build==1.2.2.post1; extra == 'packaging'
Requires-Dist: twine==6.1.0; extra == 'packaging'
Provides-Extra: spellcheck
Requires-Dist: codespell==2.4.1; extra == 'spellcheck'
Provides-Extra: tests
Requires-Dist: pytest-asyncio==0.26.0; extra == 'tests'
Requires-Dist: pytest==8.3.5; extra == 'tests'
Requires-Dist: testcontainers==4.9.2; extra == 'tests'
Provides-Extra: type-check
Requires-Dist: mypy[pydantic]==1.15.0; extra == 'type-check'
Requires-Dist: types-docker==7.1.0.20241229; extra == 'type-check'
Requires-Dist: types-pytz==2025.1.0.20250318; extra == 'type-check'
